torchbricks/__init__.py
torchbricks/brick_collection.py
torchbricks/brick_collection_utils.py
torchbricks/brick_tags.py
torchbricks/bricks.py
torchbricks/bricks_helper.py
torchbricks/collection_utils.py
torchbricks/dag.py
torchbricks/graph_plotter.py
torchbricks/tensor_conversions.py
torchbricks/bag_of_bricks/backbones.py
torchbricks/bag_of_bricks/brick_visualizer.py
torchbricks/bag_of_bricks/custom_metrics.py
torchbricks/bag_of_bricks/image_classification.py
torchbricks/bag_of_bricks/preprocessors.py
torchbricks/bag_of_bricks/task_utils.py
torchbricks-0.4.2.dist-info/licenses/LICENSE
torchbricks-0.4.2.dist-info/METADATA
torchbricks-0.4.2.dist-info/WHEEL
torchbricks-0.4.2.dist-info/top_level.txt
torchbricks-0.4.2.dist-info/RECORD
