Metadata-Version: 2.4
Name: torchbricks
Version: 0.4.2
Summary: Decoupled and modular approach to building multi-task ML models using a single model recipe for all model stages
Author-email: Peter Hviid Christiansen <PeterHviidChristiansen@gmail.com>
License: MIT License
Project-URL: Homepage, https://github.com/pete-machine/torchbricks
Keywords: torch,multi-task,machine learning
Classifier: License :: OSI Approved :: MIT License
Classifier: Programming Language :: Python
Classifier: Programming Language :: Python :: 3
Requires-Python: >=3.7
License-File: LICENSE
Requires-Dist: torch>=1.7
Requires-Dist: torchmetrics>=0.10.0
Requires-Dist: torchvision>=0.14.1
Requires-Dist: typeguard>=2.13.3
Requires-Dist: onnx>=1.14.1
Requires-Dist: pillow>=9.5.0
Dynamic: license-file
